FluencyLogisticsOperations/__init__.py
FluencyLogisticsOperations/_utils.py
FluencyLogisticsOperations/_version.py
FluencyLogisticsOperations/plc/__init__.py
FluencyLogisticsOperations/plc/core.py
FluencyLogisticsOperations/plc/node.py
FluencyLogisticsOperations/plc/segment.py
fluencylogisticsoperations-0.1.4.dist-info/licenses/LICENSE
fluencylogisticsoperations-0.1.4.dist-info/METADATA
fluencylogisticsoperations-0.1.4.dist-info/WHEEL
fluencylogisticsoperations-0.1.4.dist-info/top_level.txt
fluencylogisticsoperations-0.1.4.dist-info/RECORD
