Metadata-Version: 2.4
Name: FluencyLogisticsOperations
Version: 0.1.4
Summary: FLO Public Layer Client (PLC): dot-notation to /rpc (form-encoded), returns pandas DataFrames
Author: Braden Keith
License: Apache-2.0
Project-URL: Homepage, https://flo.bradenkeith.io
Project-URL: Source, https://github.com/fluency-logistics-operations/flo-plc
Classifier: Programming Language :: Python :: 3
Classifier: License :: OSI Approved :: Apache Software License
Classifier: Operating System :: OS Independent
Requires-Python: >=3.9
License-File: LICENSE
Requires-Dist: pandas>=2.0.0
Requires-Dist: requests>=2.32.0
Requires-Dist: urllib3>=2.2.0
Dynamic: license-file
